{"trial_id": "2", "hyperparameters": {"space": [{"class_name": "Choice", "config": {"name": "units", "default": 32, "conditions": [], "values": [32, 64, 128, 512], "ordered": true}}, {"class_name": "Choice", "config": {"name": "learning_rate", "default": 0.01, "conditions": [], "values": [0.01, 0.001, 0.0001], "ordered": true}}], "values": {"units": 512, "learning_rate": 0.0001}}, "metrics": {"metrics": {"loss": {"direction": "min", "observations": [{"value": [0.017415499314665794], "step": 19}]}, "mae": {"direction": "min", "observations": [{"value": [0.017415499314665794], "step": 19}]}, "val_loss": {"direction": "min", "observations": [{"value": [0.01994563452899456], "step": 19}]}, "val_mae": {"direction": "min", "observations": [{"value": [0.01994563452899456], "step": 19}]}}}, "score": 0.01994563452899456, "best_step": 19, "status": "COMPLETED", "message": null}